{
  "active_deployments": [
    {
      "deployment_id": "XGBoost_Default_vlatest_staging_1760510549",
      "model_name": "XGBoost_Default",
      "model_version": "latest",
      "environment": "staging",
      "status": "failed",
      "start_time": "2025-10-15T12:12:29.268262",
      "end_time": "2025-10-15T12:12:29.385393",
      "health_score": 0.0,
      "error_message": "Failed to retrieve model XGBoost_Default vlatest",
      "rollback_count": 0
    },
    {
      "deployment_id": "XGBoost_Default_vlatest_staging_1760516299",
      "model_name": "XGBoost_Default",
      "model_version": "latest",
      "environment": "staging",
      "status": "failed",
      "start_time": "2025-10-15T13:48:19.539584",
      "end_time": "2025-10-15T13:48:19.622154",
      "health_score": 0.0,
      "error_message": "Failed to retrieve model XGBoost_Default vlatest",
      "rollback_count": 0
    },
    {
      "deployment_id": "random_forest_optimized_vlatest_staging_1760520783",
      "model_name": "random_forest_optimized",
      "model_version": "latest",
      "environment": "staging",
      "status": "failed",
      "start_time": "2025-10-15T15:03:03.167787",
      "end_time": "2025-10-15T15:03:03.286570",
      "health_score": 0.0,
      "error_message": "Failed to retrieve model random_forest_optimized vlatest",
      "rollback_count": 0
    },
    {
      "deployment_id": "LightGBM_Optimized_vlatest_staging_1760522270",
      "model_name": "LightGBM_Optimized",
      "model_version": "latest",
      "environment": "staging",
      "status": "failed",
      "start_time": "2025-10-15T15:27:50.670415",
      "end_time": "2025-10-15T15:27:50.762075",
      "health_score": 0.0,
      "error_message": "Failed to retrieve model LightGBM_Optimized vlatest",
      "rollback_count": 0
    },
    {
      "deployment_id": "LightGBM_Optimized_vlatest_staging_1760522515",
      "model_name": "LightGBM_Optimized",
      "model_version": "latest",
      "environment": "staging",
      "status": "failed",
      "start_time": "2025-10-15T15:31:55.404338",
      "end_time": "2025-10-15T15:31:55.480999",
      "health_score": 0.0,
      "error_message": "Failed to retrieve model LightGBM_Optimized vlatest",
      "rollback_count": 0
    },
    {
      "deployment_id": "XGBoost_Optimized_vlatest_staging_1760522696",
      "model_name": "XGBoost_Optimized",
      "model_version": "latest",
      "environment": "staging",
      "status": "failed",
      "start_time": "2025-10-15T15:34:56.685580",
      "end_time": "2025-10-15T15:34:56.775661",
      "health_score": 0.0,
      "error_message": "Failed to retrieve model XGBoost_Optimized vlatest",
      "rollback_count": 0
    },
    {
      "deployment_id": "XGBoost_Optimized_vlatest_staging_1760522777",
      "model_name": "XGBoost_Optimized",
      "model_version": "latest",
      "environment": "staging",
      "status": "failed",
      "start_time": "2025-10-15T15:36:17.459100",
      "end_time": "2025-10-15T15:36:17.534627",
      "health_score": 0.0,
      "error_message": "Failed to retrieve model XGBoost_Optimized vlatest",
      "rollback_count": 0
    },
    {
      "deployment_id": "LightGBM_Optimized_vlatest_staging_1760525975",
      "model_name": "LightGBM_Optimized",
      "model_version": "latest",
      "environment": "staging",
      "status": "failed",
      "start_time": "2025-10-15T16:29:35.415124",
      "end_time": "2025-10-15T16:29:35.416123",
      "health_score": 0.0,
      "error_message": "Failed to retrieve model LightGBM_Optimized vlatest",
      "rollback_count": 0
    },
    {
      "deployment_id": "LightGBM_Optimized_vlatest_staging_1760526748",
      "model_name": "LightGBM_Optimized",
      "model_version": "latest",
      "environment": "staging",
      "status": "failed",
      "start_time": "2025-10-15T16:42:28.979571",
      "end_time": "2025-10-15T16:42:28.985576",
      "health_score": 0.0,
      "error_message": "Failed to retrieve model LightGBM_Optimized vlatest",
      "rollback_count": 0
    },
    {
      "deployment_id": "LightGBM_Optimized_vlatest_staging_1760528971",
      "model_name": "LightGBM_Optimized",
      "model_version": "latest",
      "environment": "staging",
      "status": "failed",
      "start_time": "2025-10-15T17:19:31.287495",
      "end_time": "2025-10-15T17:19:31.464768",
      "health_score": 0.0,
      "error_message": "Failed to retrieve model LightGBM_Optimized vlatest",
      "rollback_count": 0
    },
    {
      "deployment_id": "LightGBM_Optimized_vlatest_staging_1760529646",
      "model_name": "LightGBM_Optimized",
      "model_version": "latest",
      "environment": "staging",
      "status": "failed",
      "start_time": "2025-10-15T17:30:46.987582",
      "end_time": "2025-10-15T17:30:47.134610",
      "health_score": 0.0,
      "error_message": "Failed to retrieve model LightGBM_Optimized vlatest",
      "rollback_count": 0
    },
    {
      "deployment_id": "LightGBM_Optimized_vlatest_staging_1760530068",
      "model_name": "LightGBM_Optimized",
      "model_version": "latest",
      "environment": "staging",
      "status": "failed",
      "start_time": "2025-10-15T17:37:48.665423",
      "end_time": "2025-10-15T17:37:48.757966",
      "health_score": 0.0,
      "error_message": "Failed to retrieve model LightGBM_Optimized vlatest",
      "rollback_count": 0
    },
    {
      "deployment_id": "LightGBM_Optimized_vlatest_staging_1760530764",
      "model_name": "LightGBM_Optimized",
      "model_version": "latest",
      "environment": "staging",
      "status": "failed",
      "start_time": "2025-10-15T17:49:24.934881",
      "end_time": "2025-10-15T17:49:24.970395",
      "health_score": 0.0,
      "error_message": "Failed to retrieve model LightGBM_Optimized vlatest",
      "rollback_count": 0
    },
    {
      "deployment_id": "LightGBM_Optimized_vlatest_staging_1760531262",
      "model_name": "LightGBM_Optimized",
      "model_version": "latest",
      "environment": "staging",
      "status": "failed",
      "start_time": "2025-10-15T17:57:42.133234",
      "end_time": "2025-10-15T17:57:42.227522",
      "health_score": 0.0,
      "error_message": "Failed to retrieve model LightGBM_Optimized vlatest",
      "rollback_count": 0
    }
  ],
  "deployment_history": [],
  "last_updated": "2025-10-15T17:57:42.231042"
}